billingrails/__init__.py
billingrails/client.py
billingrails/resources/__init__.py
billingrails/resources/accounts.py
billingrails/resources/credit_grants.py
billingrails/resources/discounts.py
billingrails/resources/events.py
billingrails/resources/fees.py
billingrails/resources/invoices.py
billingrails/resources/meters.py
billingrails/resources/orders.py
billingrails/resources/payment_pages.py
billingrails/resources/payments.py
billingrails/resources/plans.py
billingrails/resources/products.py
billingrails/resources/subscriptions.py
billingrails/types/__init__.py
billingrails/types/account.py
billingrails/types/account_balances_response.py
billingrails/types/account_create.py
billingrails/types/account_debit.py
billingrails/types/account_debit_response.py
billingrails/types/account_input.py
billingrails/types/account_list_response.py
billingrails/types/account_response.py
billingrails/types/account_update.py
billingrails/types/address.py
billingrails/types/base.py
billingrails/types/credit_grant.py
billingrails/types/credit_grant_create.py
billingrails/types/credit_grant_list_response.py
billingrails/types/credit_grant_pay_response.py
billingrails/types/credit_grant_response.py
billingrails/types/discount.py
billingrails/types/discount_create.py
billingrails/types/discount_input.py
billingrails/types/discount_list_response.py
billingrails/types/discount_response.py
billingrails/types/discount_update.py
billingrails/types/error.py
billingrails/types/event.py
billingrails/types/event_batch_input.py
billingrails/types/event_batch_response.py
billingrails/types/event_input.py
billingrails/types/event_response.py
billingrails/types/fee.py
billingrails/types/fee_create.py
billingrails/types/fee_input.py
billingrails/types/fee_list_response.py
billingrails/types/fee_response.py
billingrails/types/fee_update.py
billingrails/types/interval.py
billingrails/types/invoice.py
billingrails/types/invoice_create.py
billingrails/types/invoice_input.py
billingrails-0.1.0.dist-info/licenses/LICENSE
billingrails-0.1.0.dist-info/METADATA
billingrails-0.1.0.dist-info/WHEEL
billingrails-0.1.0.dist-info/top_level.txt
billingrails-0.1.0.dist-info/RECORD
