Metadata-Version: 2.4
Name: billingrails
Version: 0.1.0
Summary: Official Python SDK for Billingrails API
Author: Billingrails
License: MIT
Project-URL: Homepage, https://github.com/billingrails/python-sdk
Project-URL: Documentation, https://docs.billingrails.com
Classifier: Programming Language :: Python :: 3
Classifier: Programming Language :: Python :: 3.7
Classifier: Programming Language :: Python :: 3.8
Classifier: Programming Language :: Python :: 3.9
Classifier: Programming Language :: Python :: 3.10
Classifier: Programming Language :: Python :: 3.11
Classifier: License :: OSI Approved :: MIT License
Classifier: Operating System :: OS Independent
Requires-Python: >=3.7
License-File: LICENSE
Requires-Dist: requests>=2.25.0
Dynamic: license-file
Dynamic: requires-python
